kontexto/__init__.py
kontexto/__main__.py
kontexto/cli.py
kontexto/graph.py
kontexto/output.py
kontexto/parser.py
kontexto/search.py
kontexto/store.py
kontexto/parsers/__init__.py
kontexto/parsers/base.py
kontexto/parsers/c_cpp_parser.py
kontexto/parsers/csharp_parser.py
kontexto/parsers/go_parser.py
kontexto/parsers/java_parser.py
kontexto/parsers/javascript_parser.py
kontexto/parsers/php_parser.py
kontexto/parsers/python_parser.py
kontexto/parsers/registry.py
kontexto/parsers/ruby_parser.py
kontexto/parsers/rust_parser.py
kontexto-0.2.0.dist-info/METADATA
kontexto-0.2.0.dist-info/WHEEL
kontexto-0.2.0.dist-info/entry_points.txt
kontexto-0.2.0.dist-info/licenses/LICENSE
kontexto-0.2.0.dist-info/RECORD
