Metadata-Version: 2.4
Name: kontexto
Version: 0.2.0
Summary: A navigable graph of your codebase for LLMs. Supports Python, JavaScript/TypeScript, Go, Rust, Java, C/C++, C#, PHP, and Ruby.
Project-URL: Homepage, https://github.com/ferdinandobons/kontexto
Project-URL: Repository, https://github.com/ferdinandobons/kontexto
Project-URL: Issues, https://github.com/ferdinandobons/kontexto/issues
Author: Ferdinando Bonsegna
License: MIT
License-File: LICENSE
Keywords: ai,cli,codebase,graph,llm,navigation
Classifier: Development Status :: 3 - Alpha
Classifier: Intended Audience :: Developers
Classifier: License :: OSI Approved :: MIT License
Classifier: Programming Language :: Python :: 3
Classifier: Programming Language :: Python :: 3.10
Classifier: Programming Language :: Python :: 3.11
Classifier: Programming Language :: Python :: 3.12
Requires-Python: >=3.10
Requires-Dist: rich>=13.0.0
Requires-Dist: tree-sitter-c-sharp>=0.23.0
Requires-Dist: tree-sitter-c>=0.23.0
Requires-Dist: tree-sitter-cpp>=0.23.0
Requires-Dist: tree-sitter-go>=0.23.0
Requires-Dist: tree-sitter-java>=0.23.0
Requires-Dist: tree-sitter-javascript>=0.23.0
Requires-Dist: tree-sitter-php>=0.23.0
Requires-Dist: tree-sitter-python>=0.23.0
Requires-Dist: tree-sitter-ruby>=0.23.0
Requires-Dist: tree-sitter-rust>=0.23.0
Requires-Dist: tree-sitter-typescript>=0.23.0
Requires-Dist: tree-sitter>=0.24.0
Requires-Dist: typer>=0.9.0
Provides-Extra: dev
Requires-Dist: bandit>=1.7.0; extra == 'dev'
Requires-Dist: mypy>=1.0.0; extra == 'dev'
Requires-Dist: pytest-cov>=4.0.0; extra == 'dev'
Requires-Dist: pytest>=7.0.0; extra == 'dev'
Requires-Dist: ruff>=0.1.0; extra == 'dev'
Requires-Dist: vulture>=2.10; extra == 'dev'
